t4wefan_tomldb-0.1.9.dist-info/licenses/LICENSE
tomldb/__init__.py
tomldb/tomldb.py
t4wefan_tomldb-0.1.9.dist-info/METADATA
t4wefan_tomldb-0.1.9.dist-info/WHEEL
t4wefan_tomldb-0.1.9.dist-info/top_level.txt
t4wefan_tomldb-0.1.9.dist-info/RECORD
