Metadata-Version: 2.4
Name: t4wefan-tomldb
Version: 0.1.9
Summary: A simple db using toml and pickle and dill.
Requires-Python: >=3.10
License-File: LICENSE
Requires-Dist: dill
Requires-Dist: filelock
Requires-Dist: setuptools
Requires-Dist: toml
Dynamic: license-file
